LICENSE
README.md
pyproject.toml
setup.py
bin/gogdiscounts
bin/gogrepo
data/gogrepo.toml
src/gogclient/__init__.py
src/gogclient/client.py
src/gogclient/db_handler.py
src/gogclient/repo.py
src/gogclient/utils.py
src/gogclient.egg-info/PKG-INFO
src/gogclient.egg-info/SOURCES.txt
src/gogclient.egg-info/dependency_links.txt
src/gogclient.egg-info/requires.txt
src/gogclient.egg-info/top_level.txt
tests/test_client.py
tests/test_db_handler.py
tests/test_utils.py