Metadata-Version: 2.1
Name: gogclient
Version: 1.0.1
Summary: An client for requests to GOG.com
Home-page: https://gitlab.com/menschel/gogclient
Author: Patrick Menschel
Author-email: Patrick Menschel <menschel.p@posteo.de>
Project-URL: Homepage, https://gitlab.com/menschel/gogclient
Project-URL: Bug Tracker, https://gitlab.com/menschel/gogclient/issues
Keywords: gogrepo,requests
Classifier: Development Status :: 4 - Beta
Classifier: Programming Language :: Python :: 3 :: Only
Classifier: License :: OSI Approved :: GNU General Public License v3 or later (GPLv3+)
Classifier: Intended Audience :: Developers
Requires-Python: >=3.7
License-File: LICENSE
Requires-Dist: requests
Requires-Dist: tqdm
Requires-Dist: lxml
Requires-Dist: tomli; python_version < "3.11"
Provides-Extra: dev
Requires-Dist: build; extra == "dev"
Requires-Dist: twine; extra == "dev"
Provides-Extra: test
Requires-Dist: pytest; extra == "test"
Requires-Dist: pytest-cov; extra == "test"
Requires-Dist: tox; extra == "test"
